README.rst
setup.cfg
setup.py
dynamodb_mapper/__init__.py
dynamodb_mapper/migration.py
dynamodb_mapper/model.py
dynamodb_mapper/transactions.py
dynamodb_mapper.egg-info/PKG-INFO
dynamodb_mapper.egg-info/SOURCES.txt
dynamodb_mapper.egg-info/dependency_links.txt
dynamodb_mapper.egg-info/requires.txt
dynamodb_mapper.egg-info/top_level.txt
dynamodb_mapper/tests/__init__.py
dynamodb_mapper/tests/test_migrations.py
dynamodb_mapper/tests/test_model.py
dynamodb_mapper/tests/test_transactions.py