Metadata-Version: 1.0
Name: dynamodb-mapper
Version: 1.8.1
Summary: Object mapper for Amazon DynamoDB
Home-page: http://dynamodb-mapper.readthedocs.org/en/latest/
Author: Jean-Tiare Le Bigot
Author-email: jtlebigot@socialludia.com
License: UNKNOWN
Platform: UNKNOWN
Classifier: Topic :: Internet
Classifier: Topic :: Database :: Front-Ends
Classifier: Operating System :: OS Independent
Classifier: Intended Audience :: Developers
Classifier: Development Status :: 4 - Beta
Classifier: Programming Language :: Python
Classifier: Programming Language :: Python :: 2.7
Classifier: License :: OSI Approved :: GNU Library or Lesser General Public License (LGPL)
